openagents_json/__init__.py
openagents_json/cli.py
openagents_json/settings.py
openagents_json/agent/__init__.py
openagents_json/agent/base.py
openagents_json/agent/capabilities.py
openagents_json/agent/config.py
openagents_json/agent/monitoring.py
openagents_json/agent/tools.py
openagents_json/agent/type_registry.py
openagents_json/agent/workflow.py
openagents_json/agent/decorator_examples/__init__.py
openagents_json/agent/decorator_examples/basic_agent.py
openagents_json/agent/decorator_examples/llm_agent.py
openagents_json/agent/decorator_examples/tool_agent.py
openagents_json/agent/utils/__init__.py
openagents_json/agent/utils/serialization.py
openagents_json/agent/utils/state.py
openagents_json/agent/utils/validation.py
openagents_json/api/__init__.py
openagents_json/api/app.py
openagents_json/api/middleware.py
openagents_json/api/router.py
openagents_json/core/__init__.py
openagents_json/core/app.py
openagents_json/core/decorators.py
openagents_json/core/registry.py
openagents_json/core/state/__init__.py
openagents_json/core/state/base.py
openagents_json/core/state/decorators.py
openagents_json/core/state/manager.py
openagents_json/core/state/serialization.py
openagents_json/core/state/managers/__init__.py
openagents_json/core/state/managers/database.py
openagents_json/core/state/managers/file.py
openagents_json/core/state/managers/memory.py
openagents_json/core/state/managers/redis.py
openagents_json/job/README.md
openagents_json/job/__init__.py
openagents_json/job/context.py
openagents_json/job/database.py
openagents_json/job/events.py
openagents_json/job/executor.py
openagents_json/job/manager.py
openagents_json/job/model.py
openagents_json/job/monitoring.py
openagents_json/job/monitoring_api.py
openagents_json/job/retry.py
openagents_json/job/storage.py
openagents_json/job/worker.py
openagents_json/job/migrations/README.md
openagents_json/job/migrations/__init__.py
openagents_json/job/migrations/create_tables.py
openagents_json/ui/README.md
openagents_json-0.1.4.dist-info/METADATA
openagents_json-0.1.4.dist-info/WHEEL
openagents_json-0.1.4.dist-info/licenses/LICENSE
openagents_json-0.1.4.dist-info/RECORD
