Metadata-Version: 2.4
Name: openagents-json
Version: 0.1.4
Summary: OpenAgents JSON framework
Project-URL: Homepage, https://github.com/nznking/openagents-json
Project-URL: Bug Tracker, https://github.com/nznking/openagents-json/issues
Author-email: OpenAgents Team <info@datakinetic.com>
License: MIT License
License-File: LICENSE
Requires-Python: >=3.8
Requires-Dist: alembic>=1.12.0
Requires-Dist: fastapi>=0.100.0
Requires-Dist: jsonschema>=4.17.3
Requires-Dist: pydantic-settings>=2.0.0
Requires-Dist: pydantic>=2.0.0
Requires-Dist: python-dotenv>=1.0.0
Requires-Dist: pyyaml>=6.0
Requires-Dist: redis>=5.0.0
Requires-Dist: sqlalchemy-utils>=0.41.0
Requires-Dist: sqlalchemy>=2.0.0
Requires-Dist: uvicorn>=0.23.0
Provides-Extra: dev
Requires-Dist: black>=23.3.0; extra == 'dev'
Requires-Dist: flake8>=6.0.0; extra == 'dev'
Requires-Dist: isort>=5.12.0; extra == 'dev'
Requires-Dist: mypy>=1.3.0; extra == 'dev'
Provides-Extra: docs
Requires-Dist: mkdocs-material>=9.1.15; extra == 'docs'
Requires-Dist: mkdocs>=1.4.3; extra == 'docs'
Requires-Dist: mkdocstrings-python>=1.1.2; extra == 'docs'
Requires-Dist: mkdocstrings>=0.22.0; extra == 'docs'
Provides-Extra: mysql
Requires-Dist: pymysql>=1.0.0; extra == 'mysql'
Provides-Extra: postgres
Requires-Dist: psycopg2>=2.9.0; extra == 'postgres'
Provides-Extra: test
Requires-Dist: pytest-asyncio>=0.21.0; extra == 'test'
Requires-Dist: pytest-cov>=4.1.0; extra == 'test'
Requires-Dist: pytest-mock>=3.10.0; extra == 'test'
Requires-Dist: pytest>=7.3.1; extra == 'test'
